yadashcomp/__init__.py
yadashcomp/bundle.js
yadashcomp/metadata.json
yadashcomp/version.py
yadashcomp-0.0.1.dist-info/DESCRIPTION.rst
yadashcomp-0.0.1.dist-info/METADATA
yadashcomp-0.0.1.dist-info/RECORD
yadashcomp-0.0.1.dist-info/WHEEL
yadashcomp-0.0.1.dist-info/metadata.json
yadashcomp-0.0.1.dist-info/top_level.txt
