Metadata-Version: 2.0
Name: yadashcomp
Version: 0.0.1
Summary: yet another dash components
Home-page: UNKNOWN
Author: pingf
Author-email: UNKNOWN
License: MIT
Platform: UNKNOWN
